rets/__init__.py
rets/exceptions.py
rets/session.py
rets/parsers/__init__.py
rets/parsers/base.py
rets/parsers/get_object.py
rets/parsers/login.py
rets/parsers/metadata.py
rets/parsers/search.py
rets/utils/__init__.py
rets/utils/get_object.py
rets/utils/search.py
rets-1.0.0.dist-info/LICENSE
rets-1.0.0.dist-info/METADATA
rets-1.0.0.dist-info/WHEEL
rets-1.0.0.dist-info/top_level.txt
rets-1.0.0.dist-info/RECORD
