Metadata-Version: 2.1
Name: rets
Version: 1.0.0
Summary: RETS Client for Real Estate Data
Home-page: https://github.com/refindlyllc/rets
Author: REfindly
Author-email: info@refindly.com
License: MIT License
Platform: UNKNOWN
Classifier: Programming Language :: Python
Classifier: Programming Language :: Python :: 2.7
Classifier: Programming Language :: Python :: 3.4
Classifier: Programming Language :: Python :: 3.5
Classifier: Programming Language :: Python :: 3.6
Classifier: Programming Language :: Python :: 3.7
Classifier: Topic :: Software Development :: Libraries :: Python Modules
Requires-Dist: requests (>=2.18.4)
Requires-Dist: xmltodict (>=0.11.0)
Requires-Dist: six (>=1.10)
Requires-Dist: future (>=0.16)
